Workbook

Sheet Journal Entries
A1: Entry | B1: Date | C1: Account | D1: Debit | E1: Credit | F1: Memo | G1: Source
A2: 1 | B2: 45658 | C2: TD Business Chequing (1000) | D2: 631.42 | F2: Opening balance | G2: 2024 TB
A3: 1 | B3: 45658 | C3: HST Recoverable (1200) | D3: 71.14 | F3: Opening balance | G3: 2024 TB
A4: 1 | B4: 45658 | C4: Computer Hardware (1741) | D4: 6380 | F4: Opening balance | G4: 2024 TB
A5: 1 | B5: 45658 | C5: Accumulated Depreciation (1742) | E5: 2420 | F5: Opening balance | G5: 2024 TB
A6: 1 | B6: 45658 | C6: HST Payable (2100) | E6: 2945.09 | F6: Opening balance | G6: 2024 TB
A7: 1 | B7: 45658 | C7: Shareholder Loan Payable (3640) | E7: 5730 | F7: Opening balance | G7: 2024 TB
A8: 1 | B8: 45658 | C8: Retained Earnings (3100) | D8: 4012.53 | F8: Opening equity | G8: 2024 TB
A9: 2 | B9: 46022 | C9: BMO Business Chequing (1010) | D9: 61675.6 | F9: Total income 2025 | G9: Bank
A10: 2 | B10: 46022 | C10: Corporate Income - Software Engineering (4300) | E10: 54580.177 | F10: Revenue | G10: Bank
A11: 2 | B11: 46022 | C11: HST Payable (2100) | E11: 7095.423 | F11: HST collected | G11: Bank
A12: 3 | B12: 46022 | C12: Vehicle Expense | D12: 6928.41 | F12: Expense | G12: Receipts
A13: 4 | B13: 46022 | C13: Depreciation (CCA) | D13: 3560.28 | F13: Expense | G13: Receipts
A14: 4 | B14: 46022 | C14: Accumulated Depreciation (1742) | E14: 3560.28 | F14: CCA | G14: CCA
A15: 5 | B15: 46022 | C15: Repairs and Maintenance | D15: 3373.18 | F15: Expense | G15: Receipts
A16: 6 | B16: 46022 | C16: Subcontractor Expense | D16: 2680.01 | F16: Expense | G16: Receipts
A17: 7 | B17: 46022 | C17: Office Expenses | D17: 2247.63 | F17: Expense | G17: Receipts
A18: 8 | B18: 46022 | C18: Advertising and Promotion | D18: 2156.43 | F18: Expense | G18: Receipts
A19: 9 | B19: 46022 | C19: Meals and Entertainment (50%) | D19: 1789.45 | F19: Expense | G19: Receipts
A20: 10 | B20: 46022 | C20: Professional Fees | D20: 1306.15 | F20: Expense | G20: Receipts
A21: 11 | B21: 46022 | C21: Insurance | D21: 1156.78 | F21: Expense | G21: Receipts
A22: 12 | B22: 46022 | C22: Property Taxes | D22: 1089.23 | F22: Expense | G22: Receipts
A23: 13 | B23: 46022 | C23: Utilities - Gas | D23: 696.17 | F23: Expense | G23: Receipts
A24: 14 | B24: 46022 | C24: Training and Education | D24: 763.33 | F24: Expense | G24: Receipts
A25: 15 | B25: 46022 | C25: Utilities - Electricity | D25: 750.41 | F25: Expense | G25: Receipts
A26: 16 | B26: 46022 | C26: Legal Fees | D26: 472.66 | F26: Expense | G26: Receipts
... A30: 20 | B30: 46022 | C30: Business Travel | D30: 2967.65 | F30: Expense | G30: Receipts
A31: 21 | B31: 46022 | C31: Shareholder Loan Payable (3640) | E31: 29540.96 | F31: Shareholder paid expenses | G31: Summary
A32: 22 | B32: 46022 | C32: Shareholder Loan Payable (3640) | D32: 57740.97 | F32: Withdrawals from bank | G32: Bank
A33: 22 | B33: 46022 | C33: BMO Business Chequing (1010) | E33: 57740.97 | F33: Cash out | G33: Bank
A34: 23 | B34: 46022 | C34: Manulife Business Advantage (1020) | D34: 1.95 | F34: Manulife ending | G34: Bank
A35: 23 | B35: 46022 | C35: BMO Business Chequing (1010) | E35: 1.95 | F35: Transfer to ML | G35: Bank
C36: TOTAL: | D36: =SUM(D2:D35) | E36: =SUM(E2:E35)

Sheet General Ledger
A1: Account | B1: Date | C1: Debit | D1: Credit | E1: Balance | F1: Memo | G1: JE #
A2: Accumulated Depreciation (1742) | B2: ='Journal Entries'!B5 | D2: ='Journal Entries'!E5 | E2: -2420 | F2: ='Journal Entries'!F5 | G2: ='Journal Entries'!A5
A3: Accumulated Depreciation (1742) | B3: ='Journal Entries'!B14 | D3: ='Journal Entries'!E14 | E3: -5980.28 | F3: ='Journal Entries'!F14 | G3: ='Journal Entries'!A14
A5: Advertising and Promotion | B5: ='Journal Entries'!B18 | C5: ='Journal Entries'!D18 | E5: 2156.43 | F5: ='Journal Entries'!F18 | G5: ='Journal Entries'!A18
A7: BMO Business Chequing (1010) | B7: ='Journal Entries'!B9 | C7: ='Journal Entries'!D9 | E7: 61675.6 | F7: ='Journal Entries'!F9 | G7: ='Journal Entries'!A9
A8: BMO Business Chequing (1010) | B8: ='Journal Entries'!B33 | D8: ='Journal Entries'!E33 | E8: 3934.63 | F8: ='Journal Entries'!F33 | G8: ='Journal Entries'!A33
A9: BMO Business Chequing (1010) | B9: ='Journal Entries'!B35 | D9: ='Journal Entries'!E35 | E9: 3932.68 | F9: ='Journal Entries'!F35 | G9: ='Journal Entries'!A35
A11: Bank Charges | B11: ='Journal Entries'!B28 | C11: ='Journal Entries'!D28 | E11: 181.29 | F11: ='Journal Entries'!F28 | G11: ='Journal Entries'!A28
A13: Business Travel | B13: ='Journal Entries'!B30 | C13: ='Journal Entries'!D30 | E13: 2967.65 | F13: ='Journal Entries'!F30 | G13: ='Journal Entries'!A30
A15: Computer Hardware (1741) | B15: ='Journal Entries'!B4 | C15: ='Journal Entries'!D4 | E15: 6380 | F15: ='Journal Entries'!F4 | G15: ='Journal Entries'!A4
A17: Corporate Income - Software Engineering (4300) | B17: ='Journal Entries'!B10 | D17: ='Journal Entries'!E10 | E17: -54580.177 | F17: ='Journal Entries'!F10 | G17: ='Journal Entries'!A10
A19: Depreciation (CCA) | B19: ='Journal Entries'!B13 | C19: ='Journal Entries'!D13 | E19: 3560.28 | F19: ='Journal Entries'!F13 | G19: ='Journal Entries'!A13
A21: HST Payable (2100) | B21: ='Journal Entries'!B6 | D21: ='Journal Entries'!E6 | E21: -2945.09 | F21: ='Journal Entries'!F6 | G21: ='Journal Entries'!A6
A22: HST Payable (2100) | B22: ='Journal Entries'!B11 | D22: ='Journal Entries'!E11 | E22: -10040.513 | F22: ='Journal Entries'!F11 | G22: ='Journal Entries'!A11
A24: HST Recoverable (1200) | B24: ='Journal Entries'!B3 | C24: ='Journal Entries'!D3 | E24: 71.14 | F24: ='Journal Entries'!F3 | G24: ='Journal Entries'!A3
A26: Insurance | B26: ='Journal Entries'!B21 | C26: ='Journal Entries'!D21 | E26: 1156.78 | F26: ='Journal Entries'!F21 | G26: ='Journal Entries'!A21
A28: Legal Fees | B28: ='Journal Entries'!B26 | C28: ='Journal Entries'!D26 | E28: 472.66 | F28: ='Journal Entries'!F26 | G28: ='Journal Entries'!A26
A30: Manulife Business Advantage (1020) | B30: ='Journal Entries'!B34 | C30: ='Journal Entries'!D34 | E30: 1.95 | F30: ='Journal Entries'!F34 | G30: ='Journal Entries'!A34
A32: Meals and Entertainment (50%) | B32: ='Journal Entries'!B19 | C32: ='Journal Entries'!D19 | E32: 1789.45 | F32: ='Journal Entries'!F19 | G32: ='Journal Entries'!A19
A34: Office Expenses | B34: ='Journal Entries'!B17 | C34: ='Journal Entries'!D17 | E34: 2247.63 | F34: ='Journal Entries'!F17 | G34: ='Journal Entries'!A17
A36: Professional Fees | B36: ='Journal Entries'!B20 | C36: ='Journal Entries'!D20 | E36: 1306.15 | F36: ='Journal Entries'!F20 | G36: ='Journal Entries'!A20
A38: Property Taxes | B38: ='Journal Entries'!B22 | C38: ='Journal Entries'!D22 | E38: 1089.23 | F38: ='Journal Entries'!F22 | G38: ='Journal Entries'!A22
A40: Repairs and Maintenance | B40: ='Journal Entries'!B15 | C40: ='Journal Entries'!D15 | E40: 3373.18 | F40: ='Journal Entries'!F15 | G40: ='Journal Entries'!A15
A42: Retained Earnings (3100) | B42: ='Journal Entries'!B8 | C42: ='Journal Entries'!D8 | E42: 4012.53 | F42: ='Journal Entries'!F8 | G42: ='Journal Entries'!A8
A44: Shareholder Loan Payable (3640) | B44: ='Journal Entries'!B7 | D44: ='Journal Entries'!E7 | E44: -5730 | F44: ='Journal Entries'!F7 | G44: ='Journal Entries'!A7
A45: Shareholder Loan Payable (3640) | B45: ='Journal Entries'!B31 | D45: ='Journal Entries'!E31 | E45: -35270.96 | F45: ='Journal Entries'!F31 | G45: ='Journal Entries'!A31
A46: Shareholder Loan Payable (3640) | B46: ='Journal Entries'!B32 | C46: ='Journal Entries'!D32 | E46: 22470.01 | F46: ='Journal Entries'!F32 | G46: ='Journal Entries'!A32
A48: Subcontractor Expense | B48: ='Journal Entries'!B16 | C48: ='Journal Entries'!D16 | E48: 2680.01 | F48: ='Journal Entries'!F16 | G48: ='Journal Entries'!A16
A50: TD Business Chequing (1000) | B50: ='Journal Entries'!B2 | C50: ='Journal Entries'!D2 | E50: 631.42 | F50: ='Journal Entries'!F2 | G50: ='Journal Entries'!A2
A52: Telephone and Internet | B52: ='Journal Entries'!B29 | C52: ='Journal Entries'!D29 | E52: 447.41 | F52: ='Journal Entries'!F29 | G52: ='Journal Entries'!A29
A54: Training and Education | B54: ='Journal Entries'!B24 | C54: ='Journal Entries'!D24 | E54: 763.33 | F54: ='Journal Entries'!F24 | G54: ='Journal Entries'!A24
A56: Utilities - Electricity | B56: ='Journal Entries'!B25 | C56: ='Journal Entries'!D25 | E56: 750.41 | F56: ='Journal Entries'!F25 | G56: ='Journal Entries'!A25
A58: Utilities - Gas | B58: ='Journal Entries'!B23 | C58: ='Journal Entries'!D23 | E58: 696.17 | F58: ='Journal Entries'!F23 | G58: ='Journal Entries'!A23
A60: Utilities - Water | B60: ='Journal Entries'!B27 | C60: ='Journal Entries'!D27 | E60: 534.77 | F60: ='Journal Entries'!F27 | G60: ='Journal Entries'!A27
A62: Vehicle Expense | B62: ='Journal Entries'!B12 | C62: ='Journal Entries'!D12 | E62: 6928.41 | F62: ='Journal Entries'!F12 | G62: ='Journal Entries'!A12
